README.md
setup.cfg
setup.py
f34f34wef4ew3r/__init__.py
f34f34wef4ew3r/foo.py
f34f34wef4ew3r.egg-info/PKG-INFO
f34f34wef4ew3r.egg-info/SOURCES.txt
f34f34wef4ew3r.egg-info/dependency_links.txt
f34f34wef4ew3r.egg-info/top_level.txt