Metadata-Version: 1.1
Name: f34f34wef4ew3r
Version: 1.1
Summary: TYPE YOUR DESCRIPTION HERE
Home-page: https://github.com/user/reponame
Author: YOUR NAME
Author-email: your.email@domain.com
License: MIT
Download-URL: https://github.com/Moneypulation/f34f34wef4ew3r/archive/refs/tags/v_11.tar.gz
Keywords: SOME,MEANINGFULL,KEYWORDS
Platform: UNKNOWN
Classifier: Development Status :: 3 - Alpha
Classifier: Intended Audience :: Developers
Classifier: Topic :: Software Development :: Build Tools
Classifier: License :: OSI Approved :: MIT License
Classifier: Programming Language :: Python :: 3
Classifier: Programming Language :: Python :: 3.4
Classifier: Programming Language :: Python :: 3.5
Classifier: Programming Language :: Python :: 3.6
